SikuliXLibrary/__init__.py
SikuliXLibrary/sikulixapp.py
SikuliXLibrary/sikulixdebug.py
SikuliXLibrary/sikuliximagepath.py
SikuliXLibrary/sikulixjclass.py
SikuliXLibrary/sikulixlibrary.py
SikuliXLibrary/sikulixlogger.py
SikuliXLibrary/sikulixpy4j.py
SikuliXLibrary/sikulixregion.py
SikuliXLibrary/sikulixsettings.py
SikuliXLibrary/version.py
robotframework_sikulixlibrary-2.0.0.dist-info/LICENSE
robotframework_sikulixlibrary-2.0.0.dist-info/METADATA
robotframework_sikulixlibrary-2.0.0.dist-info/WHEEL
robotframework_sikulixlibrary-2.0.0.dist-info/top_level.txt
robotframework_sikulixlibrary-2.0.0.dist-info/RECORD
