Metadata-Version: 2.1
Name: robotframework-sikulixlibrary
Version: 2.0.0
Summary: Robot Framework SiluliX library powered by SikuliX Java library and JPype or Py4J Python modules.
Home-page: https://github.com/adrian-evo/robotframework-sikulixlibrary
Author: Adrian V.
Author-email: avaidos@gmail.com
Classifier: Development Status :: 5 - Production/Stable
Classifier: License :: OSI Approved :: MIT License
Classifier: Operating System :: OS Independent
Classifier: Programming Language :: Python :: 3
Classifier: Topic :: Software Development :: Testing
Classifier: Framework :: Robot Framework
Classifier: Framework :: Robot Framework :: Library
Requires-Python: >=3.7,<4.0
License-File: LICENSE
Requires-Dist: robotframework (>=3.2.2)
Requires-Dist: jpype1 (>=1.2.0)
Requires-Dist: py4j (>=0.10.9.2)
